README.md
setup.py
specCreator/__init__.py
specCreator/specCreator.py
specCreator.egg-info/PKG-INFO
specCreator.egg-info/SOURCES.txt
specCreator.egg-info/dependency_links.txt
specCreator.egg-info/entry_points.txt
specCreator.egg-info/requires.txt
specCreator.egg-info/top_level.txt
specCreator/Features/__init__.py
specCreator/Features/autoPackage.py
specCreator/Features/check.py
specCreator/Features/env.py
specCreator/Features/init.py
specCreator/Features/initSpec.py
specCreator/Features/package.py
specCreator/Tools/__init__.py
specCreator/Tools/arguments.py
specCreator/Tools/cocoapodsTool.py
specCreator/Tools/commonFuncs.py
specCreator/Tools/constant.py
specCreator/Tools/fileHandle.py
specCreator/Tools/formatter.py
specCreator/Tools/gitTool.py
specCreator/Tools/mdFormatter.py
specCreator/Tools/podspecTool.py
specCreator/Tools/result.py
specCreator/Tools/resultModel.py
specCreator/Tools/shellCommand.py
specCreator/Tools/tips.py
specCreator/Tools/url.py