Metadata-Version: 1.0
Name: specCreator
Version: 1.0.22
Summary: create private pod, package framework Archive by Subspecs
Home-page: https://github.com/piaoying/specCreator
Author: handa
Author-email: 794363716@qq.com
License: MIT Licence
Keywords: pip,spec,specCreator,podspec,lib
Platform: any
